uncertainty_baselines/__init__.py
uncertainty_baselines/optimizers.py
uncertainty_baselines/optimizers_test.py
uncertainty_baselines/strategy_utils.py
uncertainty_baselines/utils.py
uncertainty_baselines/version.py
uncertainty_baselines/datasets/__init__.py
uncertainty_baselines/datasets/base.py
uncertainty_baselines/datasets/cifar.py
uncertainty_baselines/datasets/cifar_test.py
uncertainty_baselines/datasets/clinc_intent.py
uncertainty_baselines/datasets/clinc_intent_test.py
uncertainty_baselines/datasets/criteo.py
uncertainty_baselines/datasets/criteo_test.py
uncertainty_baselines/datasets/datasets.py
uncertainty_baselines/datasets/datasets_test.py
uncertainty_baselines/datasets/glue.py
uncertainty_baselines/datasets/glue_test.py
uncertainty_baselines/datasets/imagenet.py
uncertainty_baselines/datasets/imagenet_test.py
uncertainty_baselines/datasets/inception_preprocessing.py
uncertainty_baselines/datasets/jigsaw_toxic_comment.py
uncertainty_baselines/datasets/jigsaw_toxic_comment_test.py
uncertainty_baselines/datasets/mnist.py
uncertainty_baselines/datasets/mnist_test.py
uncertainty_baselines/datasets/mnli.py
uncertainty_baselines/datasets/mnli_test.py
uncertainty_baselines/datasets/svhn.py
uncertainty_baselines/datasets/svhn_test.py
uncertainty_baselines/datasets/test_utils.py
uncertainty_baselines/models/__init__.py
uncertainty_baselines/models/bert.py
uncertainty_baselines/models/bert_test.py
uncertainty_baselines/models/criteo_mlp.py
uncertainty_baselines/models/criteo_mlp_test.py
uncertainty_baselines/models/models.py
uncertainty_baselines/models/models_test.py
uncertainty_baselines/models/resnet20.py
uncertainty_baselines/models/resnet20_test.py
uncertainty_baselines/models/resnet50.py
uncertainty_baselines/models/resnet50_test.py
uncertainty_baselines/models/textcnn.py
uncertainty_baselines/models/textcnn_test.py
uncertainty_baselines/models/wide_resnet.py
uncertainty_baselines/models/wide_resnet_test.py
uncertainty_baselines-0.0.7.dist-info/LICENSE
uncertainty_baselines-0.0.7.dist-info/METADATA
uncertainty_baselines-0.0.7.dist-info/WHEEL
uncertainty_baselines-0.0.7.dist-info/top_level.txt
uncertainty_baselines-0.0.7.dist-info/RECORD
