Metadata-Version: 2.1
Name: uncertainty-baselines
Version: 0.0.7
Summary: Uncertainty Baselines
Home-page: http://github.com/google/uncertainty-baselines
Author: Uncertainty Baselines Team
Author-email: znado@google.com
License: Apache 2.0
Keywords: probabilistic programming tensorflow machine learning
Platform: UNKNOWN
Classifier: Development Status :: 3 - Alpha
Classifier: Intended Audience :: Developers
Classifier: Intended Audience :: Science/Research
Classifier: License :: OSI Approved :: Apache Software License
Classifier: Topic :: Scientific/Engineering :: Artificial Intelligence
Requires-Dist: absl-py (>=0.5.0)
Requires-Dist: numpy (>=1.7)
Requires-Dist: tensorflow-datasets (>=1.3.0)
Requires-Dist: tf-models-nightly
Requires-Dist: tf-nightly
Provides-Extra: tests
Requires-Dist: pylint (>=1.9.0) ; extra == 'tests'
